{
    "attributes": [
        {
            "description": "Time accuracy, expressed as a duration.",
            "multiplicity": null,
            "name": "accuracy",
            "type": "DV_DURATION"
        }
    ],
    "constants": [],
    "functions": [
        {
            "meaning": "Addition of a Duration to this temporal entity.",
            "name": "add",
            "parameters": [
                {
                    "name": "a_diff",
                    "type": "DV_DURATION[1]"
                }
            ],
            "return_type": "DV_TEMPORAL"
        },
        {
            "meaning": "Subtract a Duration from this temporal entity.",
            "name": "subtract",
            "parameters": [
                {
                    "name": "a_diff",
                    "type": "DV_DURATION[1]"
                }
            ],
            "return_type": "DV_TEMPORAL"
        },
        {
            "meaning": "Difference between this temporal entity and `_other_`.",
            "name": "diff",
            "parameters": [
                {
                    "name": "other",
                    "type": "DV_TEMPORAL[1]"
                }
            ],
            "return_type": "DV_DURATION"
        }
    ],
    "meta_info": {
        "base_type": "DV_ABSOLUTE_QUANTITY",
        "classifier": "Class",
        "description": "Specialised temporal variant of `DV_ABSOLUTE_QUANTITY` whose diff type is `DV_DURATION`.",
        "name": "DV_TEMPORAL"
    }
}